suit/__init__.py
suit/__main__.py
suit/__version__.py
suit/collector.py
suit/config.py
suit/console.py
suit/py.typed
suit/targets.py
suit/cli/__init__.py
suit/cli/_scripts.py
suit/cli/_targets.py
suit/cli/cli.py
suit/cli/executor.py
suit/cli/fake_executor.py
suit/scripts/__init__.py
suit/scripts/resolver.py
suit/scripts/specs.py
suit/scripts/types.py
python_suit-0.0.2.dist-info/METADATA
python_suit-0.0.2.dist-info/WHEEL
python_suit-0.0.2.dist-info/entry_points.txt
python_suit-0.0.2.dist-info/top_level.txt
python_suit-0.0.2.dist-info/RECORD
